voiceCalc/__init__.py
voiceCalc/add.py
voiceCalc/divide.py
voiceCalc/multiply.py
voiceCalc/subtract.py
voiceCalc/voiceCalc.py
voiceCalc-2.2.2.dist-info/LICENSE
voiceCalc-2.2.2.dist-info/METADATA
voiceCalc-2.2.2.dist-info/WHEEL
voiceCalc-2.2.2.dist-info/top_level.txt
voiceCalc-2.2.2.dist-info/RECORD
