Metadata-Version: 2.1
Name: voiceCalc
Version: 2.2.2
Summary: A simple calculator but controlled by voice.
Home-page: UNKNOWN
Author: Deo Krishna
Author-email: deo2k09@gmail.com
License: UNKNOWN
Platform: UNKNOWN
Classifier: Programming Language :: Python :: 3
Classifier: License :: OSI Approved :: MIT License
Classifier: Operating System :: OS Independent
Requires-Python: >=3.10
License-File: LICENSE
Requires-Dist: SpeechRecognition
Requires-Dist: pyaudio
Requires-Dist: VCIBD2
